docker_harbormaster/__init__.py
docker_harbormaster/cli.py
docker_harbormaster/conftest.py
docker_harbormaster/utils.py
docker_harbormaster-0.3.4.dist-info/LICENSE
docker_harbormaster-0.3.4.dist-info/METADATA
docker_harbormaster-0.3.4.dist-info/WHEEL
docker_harbormaster-0.3.4.dist-info/entry_points.txt
docker_harbormaster-0.3.4.dist-info/RECORD
