Metadata-Version: 2.1
Name: docker-harbormaster
Version: 0.3.4
Summary: A supervisor for docker-compose apps.
Home-page: https://harbormaster.readthedocs.io/en/latest/
License: AGPL-3.0-or-later
Author: Stavros Korokithakis
Author-email: hi@stavros.io
Requires-Python: >=3.8,<4
Classifier: License :: OSI Approved :: GNU Affero General Public License v3 or later (AGPLv3+)
Classifier: Programming Language :: Python :: 3
Classifier: Programming Language :: Python :: 3.8
Classifier: Programming Language :: Python :: 3.9
Classifier: Programming Language :: Python :: 3.10
Classifier: Programming Language :: Python :: 3.11
Requires-Dist: PyYAML (>=6.0.0)
Requires-Dist: attrs (>=21.2.0)
Requires-Dist: click (>=8.1.3)
Requires-Dist: click-help-colors (>=0.9.1)
Project-URL: Repository, https://gitlab.com/stavros/harbormaster
